README.md
setup.py
cqh_pyproxy.egg-info/PKG-INFO
cqh_pyproxy.egg-info/SOURCES.txt
cqh_pyproxy.egg-info/dependency_links.txt
cqh_pyproxy.egg-info/entry_points.txt
cqh_pyproxy.egg-info/requires.txt
cqh_pyproxy.egg-info/top_level.txt
pyproxy/__init__.py
pyproxy/main.py